oarepo_cli/__init__.py
oarepo_cli/cli.py
oarepo_cli/config.py
oarepo_cli/package_versions.py
oarepo_cli/utils.py
oarepo_cli/build_command/__init__.py
oarepo_cli/build_command/cli.py
oarepo_cli/build_command/wizard.py
oarepo_cli/build_command/steps/__init__.py
oarepo_cli/develop/__init__.py
oarepo_cli/develop/cli.py
oarepo_cli/develop/config.py
oarepo_cli/develop/controller.py
oarepo_cli/develop/wizard.py
oarepo_cli/develop/runners/__init__.py
oarepo_cli/develop/runners/docker.py
oarepo_cli/develop/runners/local.py
oarepo_cli/develop/steps/__init__.py
oarepo_cli/develop/steps/check_db.py
oarepo_cli/develop/steps/check_dependencies.py
oarepo_cli/develop/steps/check_s3_location.py
oarepo_cli/develop/steps/check_search.py
oarepo_cli/develop/steps/check_site.py
oarepo_cli/develop/steps/check_ui.py
oarepo_cli/develop/steps/check_venv.py
oarepo_cli/develop/steps/develop_step.py
oarepo_cli/develop/steps/editor_support.py
oarepo_cli/format/__init__.py
oarepo_cli/format/cli.py
oarepo_cli/format/wizard.py
oarepo_cli/format/steps/__init__.py
oarepo_cli/format/steps/base.py
oarepo_cli/format/steps/format_javascript.py
oarepo_cli/format/steps/format_jinja.py
oarepo_cli/format/steps/format_python.py
oarepo_cli/initialize/__init__.py
oarepo_cli/initialize/cli.py
oarepo_cli/initialize/wizard.py
oarepo_cli/initialize/steps/__init__.py
oarepo_cli/initialize/steps/create_monorepo.py
oarepo_cli/initialize/steps/initialize_directory.py
oarepo_cli/initialize/steps/install_nrp_cli.py
oarepo_cli/invenio/__init__.py
oarepo_cli/invenio/cli.py
oarepo_cli/invenio/wizard.py
oarepo_cli/invenio/steps/__init__.py
oarepo_cli/invenio/steps/run_invenio.py
oarepo_cli/kill/__init__.py
oarepo_cli/local/__init__.py
oarepo_cli/local/add/__init__.py
oarepo_cli/local/add/cli.py
oarepo_cli/local/add/wizard.py
oarepo_cli/local/add/steps/__init__.py
oarepo_cli/local/add/steps/add_local.py
oarepo_cli/local/add/steps/install.py
oarepo_cli/local/remove/__init__.py
oarepo_cli/local/remove/cli.py
oarepo_cli-11.1.38.dist-info/METADATA
oarepo_cli-11.1.38.dist-info/WHEEL
oarepo_cli-11.1.38.dist-info/entry_points.txt
oarepo_cli-11.1.38.dist-info/top_level.txt
oarepo_cli-11.1.38.dist-info/RECORD
