Metadata-Version: 2.1
Name: oarepo-cli
Version: 11.1.38
Summary: Utilities for managing invenio monorepo
Requires-Dist: colorama
Requires-Dist: click
Requires-Dist: cookiecutter
Requires-Dist: tomlkit
Requires-Dist: deepmerge
Requires-Dist: gitpython
Requires-Dist: pydriller
Requires-Dist: watchdog
Requires-Dist: importlib-metadata
Requires-Dist: ruamel.yaml
Requires-Dist: tomli-w
Requires-Dist: requirements-parser
Requires-Dist: python-dotenv
Requires-Dist: minio
Requires-Dist: redis
Requires-Dist: psycopg[binary]
Requires-Dist: pika
Requires-Dist: opensearch-py
Requires-Dist: black
Requires-Dist: isort
Requires-Dist: autoflake
Requires-Dist: licenseheaders
Requires-Dist: djlint
Requires-Dist: psutil
